challengerteco/Challenger.py
challengerteco/__init__.py
challengerteco-0.1.20.dist-info/METADATA
challengerteco-0.1.20.dist-info/WHEEL
challengerteco-0.1.20.dist-info/RECORD
