Metadata-Version: 2.1
Name: challengerteco
Version: 0.1.20
Summary: Clase para manejo de challenger en la nube
Author: Eduardo Pagnone
Author-email: mlopsaa@teco.com.ar
Requires-Python: >=3.7,<4.0
Classifier: Programming Language :: Python :: 3
Classifier: Programming Language :: Python :: 3.7
Classifier: Programming Language :: Python :: 3.8
Classifier: Programming Language :: Python :: 3.9
Classifier: Programming Language :: Python :: 3.10
Classifier: Programming Language :: Python :: 3.11
